uw_gws/VERSION
uw_gws/__init__.py
uw_gws/dao.py
uw_gws/exceptions.py
uw_gws/models.py
uw_gws/test.py
uw_gws/utilities.py
uw_gws/resources/gws/file/group_sws/v3/search_member_javerage
uw_gws/resources/gws/file/group_sws/v3/search_member_javerage_type_effective
uw_gws/resources/gws/file/group_sws/v3/search_stem_cal_sea
uw_gws/resources/gws/file/group_sws/v3/group/course_2012aut-train102a/index.html
uw_gws/resources/gws/file/group_sws/v3/group/u_acadev_bad_members/member
uw_gws/resources/gws/file/group_sws/v3/group/u_acadev_tester/history
uw_gws/resources/gws/file/group_sws/v3/group/u_acadev_tester/history_activity_membership_start_1626215400000
uw_gws/resources/gws/file/group_sws/v3/group/u_acadev_tester/history_id_eight
uw_gws/resources/gws/file/group_sws/v3/group/u_acadev_tester/index.html
uw_gws/resources/gws/file/group_sws/v3/group/u_acadev_tester/effective_member/index.html
uw_gws/resources/gws/file/group_sws/v3/group/u_acadev_tester/effective_member/javerage
uw_gws/resources/gws/file/group_sws/v3/group/u_acadev_tester/member/index.html
uw_gws/resources/gws/file/group_sws/v3/group/u_acadev_tester/member/javerage
uw_gws/resources/gws/file/group_sws/v3/group/u_acadev_unittest/effective_member_view_count
uw_gws/resources/gws/file/group_sws/v3/group/u_acadev_unittest/index.html
uw_gws/resources/gws/file/group_sws/v3/group/u_acadev_unittest/effective_member/eight
uw_gws/resources/gws/file/group_sws/v3/group/u_acadev_unittest/effective_member/index.html
uw_gws/resources/gws/file/group_sws/v3/group/u_acadev_unittest/effective_member/javerage
uw_gws/resources/gws/file/group_sws/v3/group/u_acadev_unittest/member/eight_seven
uw_gws/resources/gws/file/group_sws/v3/group/u_acadev_unittest/member/index.html
uw_gws/resources/gws/file/group_sws/v3/group/u_acadev_unittest/member/seven
uw_gws/tests/__init__.py
uw_gws/tests/test_group.py
uw_restclients_gws-2.3.9.dist-info/licenses/LICENSE
uw_restclients_gws-2.3.9.dist-info/METADATA
uw_restclients_gws-2.3.9.dist-info/WHEEL
uw_restclients_gws-2.3.9.dist-info/top_level.txt
uw_restclients_gws-2.3.9.dist-info/RECORD
